straightemail/__init__.py
straightemail/send_email.py
straightemail-0.0.5.dist-info/METADATA
straightemail-0.0.5.dist-info/WHEEL
straightemail-0.0.5.dist-info/top_level.txt
straightemail-0.0.5.dist-info/RECORD
