Metadata-Version: 2.1
Name: straightemail
Version: 0.0.5
Summary: straightemail is a package built with a motive to ease the email functionality as much as possible.
Author: Shreejeet Sahay
Author-email: ssahay.official@gmail.com
